patrolify/__init__.py
patrolify/admin/__init__.py
patrolify/admin/admin_api.py
patrolify/admin/frontend_dist/assets/allPaths-cuJB7CbI.js
patrolify/admin/frontend_dist/assets/allPathsLoader-iNouCTEK.js
patrolify/admin/frontend_dist/assets/blueprint-icons-16-A6x-eFv8.woff2
patrolify/admin/frontend_dist/assets/blueprint-icons-16-AbW_Hfh7.woff
patrolify/admin/frontend_dist/assets/blueprint-icons-16-As7MhKDx.svg
patrolify/admin/frontend_dist/assets/blueprint-icons-16-EQg0pAuF.eot
patrolify/admin/frontend_dist/assets/blueprint-icons-16-X7NQcG0c.ttf
patrolify/admin/frontend_dist/assets/blueprint-icons-20-6KJtW0h6.eot
patrolify/admin/frontend_dist/assets/blueprint-icons-20-8lZxjX0E.svg
patrolify/admin/frontend_dist/assets/blueprint-icons-20-GVvvSZz3.woff
patrolify/admin/frontend_dist/assets/blueprint-icons-20-RhhrKgyU.ttf
patrolify/admin/frontend_dist/assets/blueprint-icons-20-_VjthUhv.woff2
patrolify/admin/frontend_dist/assets/index-6QKa2Ynx.js
patrolify/admin/frontend_dist/assets/index-Bfvs1Dps.js
patrolify/admin/frontend_dist/assets/index-Zttfj1Qn.css
patrolify/admin/frontend_dist/assets/index-s_3b95Qx.js
patrolify/admin/frontend_dist/assets/splitPathsBySizeLoader-zeqlQPfm.js
patrolify/admin/frontend_dist/index.html
patrolify/admin/frontend_dist/patrolify-logo.svg
patrolify/admin/server.py
patrolify/admin/web/.eslintrc.cjs
patrolify/admin/web/.gitignore
patrolify/admin/web/README.md
patrolify/admin/web/index.html
patrolify/admin/web/package.json
patrolify/admin/web/public/patrolify-logo.svg
patrolify/admin/web/src/App.css
patrolify/admin/web/src/App.jsx
patrolify/admin/web/src/CheckDetailPage.jsx
patrolify/admin/web/src/CheckerDetailPage.css
patrolify/admin/web/src/CheckerDetailPage.jsx
patrolify/admin/web/src/CheckerLayout.jsx
patrolify/admin/web/src/JobAllStatusSpan.jsx
patrolify/admin/web/src/Navbar.jsx
patrolify/admin/web/src/fileexplorer/index.jsx
patrolify/admin/web/src/homepage/HomePage.css
patrolify/admin/web/src/homepage/HomePage.jsx
patrolify-0.1.13.dist-info/METADATA
patrolify-0.1.13.dist-info/WHEEL
patrolify-0.1.13.dist-info/entry_points.txt
patrolify-0.1.13.dist-info/RECORD
