Metadata-Version: 2.1
Name: patrolify
Version: 0.1.13
Summary: 
Author: laixintao
Author-email: laixintaoo@gmail.com
Requires-Python: >=3.10,<4.0
Classifier: Programming Language :: Python :: 3
Classifier: Programming Language :: Python :: 3.10
Classifier: Programming Language :: Python :: 3.11
Classifier: Programming Language :: Python :: 3.12
Requires-Dist: click (>=8.1.7,<9.0.0)
Requires-Dist: flask (>=3.0.0,<4.0.0)
Requires-Dist: prometheus-client (>=0.19.0,<0.20.0)
Requires-Dist: rq (>=1.15.1,<2.0.0)
Requires-Dist: rq-scheduler (>=0.13.1,<0.14.0)
Requires-Dist: waitress (>=2.1.2,<3.0.0)
